termcopy/__init__.py
termcopy/cli.py
termcopy-0.2.0.dist-info/licenses/LICENSE
termcopy-0.2.0.dist-info/METADATA
termcopy-0.2.0.dist-info/WHEEL
termcopy-0.2.0.dist-info/entry_points.txt
termcopy-0.2.0.dist-info/top_level.txt
termcopy-0.2.0.dist-info/RECORD
