Metadata-Version: 2.4
Name: termcopy
Version: 0.2.0
Summary: A CLI tool for terminal clipboard operations
Home-page: https://github.com/scaryPonens/termco-py
Author: scaryPonens
Author-email: Reuben Peter-Paul <reuben.peterpaul@gmail.com>
License: MIT
Project-URL: Homepage, https://github.com/scaryPonens/termco-py
Project-URL: Repository, https://github.com/scaryPonens/termco-py
Project-URL: Issues, https://github.com/scaryPonens/termco-py/issues
Classifier: Development Status :: 4 - Beta
Classifier: Intended Audience :: Developers
Classifier: License :: OSI Approved :: MIT License
Classifier: Operating System :: OS Independent
Classifier: Programming Language :: Python :: 3
Classifier: Programming Language :: Python :: 3.7
Classifier: Programming Language :: Python :: 3.8
Classifier: Programming Language :: Python :: 3.9
Classifier: Programming Language :: Python :: 3.10
Classifier: Programming Language :: Python :: 3.11
Classifier: Programming Language :: Python :: 3.12
Requires-Python: >=3.7
License-File: LICENSE
Provides-Extra: dev
Requires-Dist: pytest>=6.0.0; extra == "dev"
Requires-Dist: pytest-cov>=2.10.0; extra == "dev"
Requires-Dist: black>=21.0.0; extra == "dev"
Requires-Dist: flake8>=3.8.0; extra == "dev"
Requires-Dist: mypy>=0.800; extra == "dev"
Dynamic: author
Dynamic: home-page
Dynamic: license-file
Dynamic: requires-python
